iflow_mcp_kaggle_mcp-0.1.2.dist-info/licenses/LICENSE
kaggle_mcp/__init__.py
kaggle_mcp/server.py
kaggle_mcp/setup_helper.py
kaggle_mcp/tools/__init__.py
kaggle_mcp/tools/auth.py
kaggle_mcp/tools/competitions.py
kaggle_mcp/tools/config.py
kaggle_mcp/tools/datasets.py
kaggle_mcp/tools/kernels.py
kaggle_mcp/tools/models.py
iflow_mcp_kaggle_mcp-0.1.2.dist-info/METADATA
iflow_mcp_kaggle_mcp-0.1.2.dist-info/WHEEL
iflow_mcp_kaggle_mcp-0.1.2.dist-info/entry_points.txt
iflow_mcp_kaggle_mcp-0.1.2.dist-info/top_level.txt
iflow_mcp_kaggle_mcp-0.1.2.dist-info/RECORD
