Metadata-Version: 2.4
Name: iflow-mcp_kaggle-mcp
Version: 0.1.2
Summary: Kaggle API integration through the Model Context Protocol
Home-page: https://github.com/54yyyu/kaggle-mcp
Author: Kaggle MCP Contributors
Author-email: Kaggle MCP Contributors <example@example.com>
License: MIT
Project-URL: Homepage, https://github.com/username/kaggle-mcp
Project-URL: Bug Tracker, https://github.com/username/kaggle-mcp/issues
Classifier: Programming Language :: Python :: 3
Classifier: License :: OSI Approved :: MIT License
Classifier: Operating System :: OS Independent
Requires-Python: >=3.8
License-File: LICENSE
Requires-Dist: mcp[cli]>=1.3.0
Requires-Dist: kaggle>=1.5.0
Dynamic: author
Dynamic: home-page
Dynamic: license-file
Dynamic: requires-python
